flask_api_handler/__init__.py
flask_api_handler/api_handler.py
flask_api_handler-0.1.6.dist-info/METADATA
flask_api_handler-0.1.6.dist-info/RECORD
flask_api_handler-0.1.6.dist-info/WHEEL
flask_api_handler-0.1.6.dist-info/top_level.txt
