Metadata-Version: 2.1
Name: flask-api-handler
Version: 0.1.6
Summary: A small wrapper for flask app to ease the endpoints creation
Home-page: https://github.com/shahar84/flask-api-handler
Author: Shahar Polak
Author-email: makore.shahar@gmail.com
License: MIT
Keywords: Flask API REST flask-restful
Platform: UNKNOWN
Classifier: Development Status :: 3 - Alpha
Classifier: Intended Audience :: Developers
Classifier: Topic :: Software Development :: Build Tools
Classifier: License :: OSI Approved :: MIT License
Classifier: Programming Language :: Python :: 2
Classifier: Programming Language :: Python :: 2.7
Classifier: Programming Language :: Python :: 3
Classifier: Programming Language :: Python :: 3.4
Classifier: Programming Language :: Python :: 3.5
Classifier: Programming Language :: Python :: 3.6
Requires-Dist: flask
